{
  "case_number": "1997-04",
  "status": "decision",
  "vol": "M26G (1998)",
  "pdf_page_start": 130,
  "pdf_page_end": 132,
  "disposition": "not_sustained",
  "vote": "21-0",
  "has_dissent": false,
  "bco_cited_as": [
    "BCO 43-1",
    "BCO 31-7",
    "BCO 42-9",
    "BCO 32-4",
    "BCO 35-1",
    "BCO 35-5"
  ],
  "topics": [
    "church membership rolls",
    "presbytery authority",
    "complaint procedure",
    "due process",
    "constitutional procedure"
  ],
  "synopsis": "Central Carolina Presbytery did not act unconstitutionally in denying the complaint of Conrad, et al. against the Session of Prosperity Presbyterian Church. Although various actions taken by the parties were open to differing opinions and interpretations, the complainants failed to demonstrate any unconstitutional procedure or violations of the PCA Book of Church Order."
}
