{
  "case_number": "2002-13",
  "status": "decision",
  "vol": "GA 29",
  "pdf_page_start": 95,
  "pdf_page_end": 105,
  "disposition": "denied",
  "vote": "18-0",
  "has_dissent": false,
  "bco_cited_as": [
    "BCO 40-5",
    "BCO 43-1",
    "BCO 15-1",
    "BCO 31-2"
  ],
  "topics": [
    "memorials",
    "constitutional procedure",
    "judicial process",
    "ecclesiastical due process",
    "presbytery authority"
  ],
  "synopsis": "The Standing Judicial Commission held that Philadelphia Presbytery did not act unconstitutionally in appointing a commission to hear a memorial from RE David Lachman and adopting its report. The Commission found no evidence of gross unconstitutional proceedings by the Presbytery or its subordinate commission, and upheld the Presbytery's procedures for handling memorials under BCO 40-5."
}
