{
  "case_number": "2023-14",
  "status": "decision",
  "vol": "51st_pcaga_2024.pdf",
  "pdf_page_start": 933,
  "pdf_page_end": 957,
  "disposition": "other",
  "vote": "19-0",
  "has_dissent": true,
  "bco_cited_as": ["40-5", "20-4", "20-5", "24-7", "15-4", "15-1", "14-6", "40-1", "11-3", "25-11", "34-4", "43-1"],
  "topics": ["BCO 40-5 delinquency", "congregational election procedure", "slate voting", "ballot vs. standing vote", "associate pastor installation", "unauthorized commission", "call to ministry", "presbytery oversight"],
  "synopsis": "The SJC, pursuant to citation by the 50th General Assembly under BCO 40-5, found that Northwest Georgia Presbytery erred egregiously in approving calls and installing three candidates as associate pastors through a constitutionally deficient election process (slate voting, standing vote, failure to record number of voters present). The SJC stayed all further proceedings and declined to annul the installations, finding no PCA precedent for such relief."
}
